MANIFEST.in
README.rst
requirements.txt
setup.py
geotagger/__init__.py
geotagger/__main__.py
geotagger/core.py
geotagger/exif.py
geotagger/gpx.py
geotagger/moves.py
geotagger/settings.py
geotagger/utils.py
geotagger.egg-info/PKG-INFO
geotagger.egg-info/SOURCES.txt
geotagger.egg-info/dependency_links.txt
geotagger.egg-info/entry_points.txt
geotagger.egg-info/requires.txt
geotagger.egg-info/top_level.txt
geotagger/packages/__init__.py
geotagger/packages/exiftool.py
geotagger/templates/gpx.xml