Metadata-Version: 1.1
Name: geotagger
Version: 0.0.3
Summary: Geotag photos with exiftool based on your Moves app history
Home-page: https://github.com/jakubroztocil/geotagger
Author: Jakub Roztocil
Author-email: jakub@roztocil.co
License: MIT
Download-URL: https://github.com/jakubroztocil/geotagger
Platform: UNKNOWN
